agentdev/__init__.py
agentdev/constants.py
agentdev/langgraph_util.py
agentdev/version.py
agentdev/base/__base.py
agentdev/base/__init__.py
agentdev/base/component.py
agentdev/base/function_tool.py
agentdev/base/memory.py
agentdev/base/model.py
agentdev/base/prompt.py
agentdev/components/__init__.py
agentdev/components/bailian_intention_center.py
agentdev/components/bailian_plugin_center.py
agentdev/components/bailian_rag.py
agentdev/components/bailian_search.py
agentdev/components/bailian_search_lite.py
agentdev/components/image_generation.py
agentdev/components/juhe_tools.py
agentdev/components/local_memory.py
agentdev/components/redis_memory.py
agentdev/components/research.py
agentdev/errors/__init__.py
agentdev/errors/error.py
agentdev/errors/service_errors.py
agentdev/mcp_utils/__init__.py
agentdev/mcp_utils/mcp_wrapper.py
agentdev/mcp_utils/server.py
agentdev/models/__init__.py
agentdev/models/function_call.py
agentdev/models/llm.py
agentdev/schemas/__init__.py
agentdev/schemas/bailian_copilot.py
agentdev/schemas/bailian_message_schemas.py
agentdev/schemas/llm_schemas.py
agentdev/schemas/message_schemas.py
agentdev/server/__init__.py
agentdev/server/fastapi_server.py
agentdev/tracing/__init__.py
agentdev/tracing/aliyun_tracer.py
agentdev/tracing/base.py
agentdev/tracing/dashscope_log.py
agentdev/tracing/tracing_metric.py
agentdev/tracing/wrapper.py
agentdev/utils/__init__.py
agentdev/utils/api_key_util.py
agentdev/utils/asyncio_util.py
agentdev/utils/mcp_util.py
agentdev/utils/message_util.py
agentdev/utils/prompts.py
agentdev/utils/search_util.py
agentdev/utils/utils.py
tests/__init__.py
tests/test_errors.py
tests/test_function_call.py
tests/test_function_tool.py
tests/test_llm.py
tests/test_memory.py
tests/test_prompt.py
tests/test_tracing.py
tests/components/__init__.py
tests/components/test_intention.py
tests/components/test_plugin_center.py
tests/components/test_rag.py
tests/components/test_redis_memory.py
tests/components/test_search.py
agentdev-0.5.0.dist-info/METADATA
agentdev-0.5.0.dist-info/WHEEL
agentdev-0.5.0.dist-info/top_level.txt
agentdev-0.5.0.dist-info/RECORD
