Metadata-Version: 2.1
Name: agentdev
Version: 0.5.0
Summary: AgentDev provides basic components that used on Bailian.platform with unified API
Home-page: https://code.alibaba-inc.com/dashscope/bailiansdk
Author: Bailian Team
Author-email: zhangzhicheng.zzc@alibaba-inc.com
License: Apache License 2.0
Keywords: python,Agent,AIGC,LLM,Components
Requires-Dist: aliyun-trace
Requires-Dist: anyio
Requires-Dist: asgiref~=3.8.1
Requires-Dist: dashscope
Requires-Dist: fastapi
Requires-Dist: instructor~=1.7.9
Requires-Dist: jinja2~=3.1.6
Requires-Dist: json5
Requires-Dist: jsonref~=1.1.0
Requires-Dist: mcp
Requires-Dist: nacos-sdk-python==1.0.0
Requires-Dist: openai
Requires-Dist: opentelemetry-api
Requires-Dist: opentelemetry-exporter-otlp
Requires-Dist: opentelemetry-sdk
Requires-Dist: pydantic~=2.10.6
Requires-Dist: pytest
Requires-Dist: pytest-mock
Requires-Dist: requests
Requires-Dist: setuptools
Requires-Dist: starlette
Requires-Dist: typing-extensions
Requires-Dist: uvicorn
